mbsim/mbsim.py
mbsim/sim.py
mbsim/ui.py
mbsim-0.1.2.dist-info/LICENSE.txt
mbsim-0.1.2.dist-info/METADATA
mbsim-0.1.2.dist-info/WHEEL
mbsim-0.1.2.dist-info/entry_points.txt
mbsim-0.1.2.dist-info/top_level.txt
mbsim-0.1.2.dist-info/RECORD
