Metadata-Version: 2.1
Name: mbsim
Version: 0.1.2
Summary: A Modbus Simulator
Home-page: https://gitlab.com/nee2c/mbsim
Author: nee2c
Author-email: nico2c3c@gmail.com
License: MIT
Project-URL: Documentation, https://mbsim.readthedocs.io/en/latest/
Platform: Linux
Classifier: Development Status :: 4 - Beta
Classifier: License :: OSI Approved :: MIT License
Classifier: Programming Language :: Python
Classifier: Programming Language :: Python :: 3
Classifier: Programming Language :: Python :: 3 :: Only
Classifier: Programming Language :: Python :: Implementation :: CPython
Requires-Python: >=3.5
License-File: LICENSE.txt
Requires-Dist: mbsim-core
Requires-Dist: importlib-metadata ; python_version < "3.8"
Provides-Extra: dev
Requires-Dist: pre-commit ; extra == 'dev'
Requires-Dist: pytest ; extra == 'dev'
Requires-Dist: pytest-cov ; extra == 'dev'
Requires-Dist: setuptools ; extra == 'dev'
Requires-Dist: tox ; extra == 'dev'
